Workbook

Sheet Dataset
A1: Bank Name | B1: city | C1: stalp | D1: zip | E1: RepDte | F1: Reporting Year | G1: Employees | H1: Total Assets(000) | I1: CashBalance(000) | J1: Total Liabilities/Capital (000) | K1: Liabilities(000) | L1: Deposits | M1: Bank Classification | N1: Reserve Ratio | O1: Cash Requirements | P1: Liabilities /Total Assets | Q1: Total Asset/Employees | R1: CashBalance/Cash Requirements | U1: Reserve Ratio = Deposits/Cash Requirement
A2: 1ST CAPITAL BANK | B2: Salinas | C2: CA | D2: 93901 | E2: 43738 | F2: =YEAR(E2) -> 2019 | G2: 85 | H2: 637456 | I2: 53476 | J2: 637456 | K2: 571121 | L2: 565655 | M2: =IF(H2>1000000,"Large",IF(H2<100000,"Small","Medium")) -> Medium | N2: =VLOOKUP(C2,Lookup!$A$2:$D$5,MATCH(M2,Lookup!$A$1:$D$1,0),FALSE) -> 0.09 | O2: =L2*N2 -> 50908.95 | P2: =K2/H2 -> 0.89593792 | Q2: =H2/G2 -> 7499.4824 | R2: =I2/O2 -> 1.0504243
A3: 1ST CAPITAL BANK | B3: Salinas | C3: CA | D3: 93901 | E3: 44104 | F3: =YEAR(E3) -> 2020 | G3: 94 | H3: 749022 | I3: 45680 | J3: 749022 | K3: 676634 | L3: 661575 | M3: =IF(H3>1000000,"Large",IF(H3<100000,"Small","Medium")) -> Medium | N3: =VLOOKUP(C3,Lookup!$A$2:$D$5,MATCH(M3,Lookup!$A$1:$D$1,0),FALSE) -> 0.09 | O3: =L3*N3 -> 59541.75 | P3: =K3/H3 -> 0.90335664 | Q3: =H3/G3 -> 7968.3191 | R3: =I3/O3 -> 0.76719277
A4: 1ST CAPITAL BANK | B4: Salinas | C4: CA | D4: 93901 | E4: 44469 | F4: =YEAR(E4) -> 2021 | G4: 93 | H4: 1009352 | I4: 131582 | J4: 1009352 | K4: 930792 | L4: 926395 | M4: =IF(H4>1000000,"Large",IF(H4<100000,"Small","Medium")) -> Large | N4: =VLOOKUP(C4,Lookup!$A$2:$D$5,MATCH(M4,Lookup!$A$1:$D$1,0),FALSE) -> 0.08 | O4: =L4*N4 -> 74111.6 | P4: =K4/H4 -> 0.92216789 | Q4: =H4/G4 -> 10853.247 | R4: =I4/O4 -> 1.7754576
A5: 1ST COMMUNITY BANK | B5: Sherrard | C5: IL | D5: 61281 | E5: 43738 | F5: =YEAR(E5) -> 2019 | G5: 18 | H5: 64436 | I5: 7275 | J5: 64436 | K5: 57779 | L5: 57575 | M5: =IF(H5>1000000,"Large",IF(H5<100000,"Small","Medium")) -> Small | N5: =VLOOKUP(C5,Lookup!$A$2:$D$5,MATCH(M5,Lookup!$A$1:$D$1,0),FALSE) -> 0.09 | O5: =L5*N5 -> 5181.75 | P5: =K5/H5 -> 0.89668819 | Q5: =H5/G5 -> 3579.7778 | R5: =I5/O5 -> 1.4039658
A6: 1ST COMMUNITY BANK | B6: Sherrard | C6: IL | D6: 61281 | E6: 44104 | F6: =YEAR(E6) -> 2020 | G6: 18 | H6: 68303 | I6: 14220 | J6: 68303 | K6: 61477 | L6: 57268 | M6: =IF(H6>1000000,"Large",IF(H6<100000,"Small","Medium")) -> Small | N6: =VLOOKUP(C6,Lookup!$A$2:$D$5,MATCH(M6,Lookup!$A$1:$D$1,0),FALSE) -> 0.09 | O6: =L6*N6 -> 5154.12 | P6: =K6/H6 -> 0.90006295 | Q6: =H6/G6 -> 3794.6111 | R6: =I6/O6 -> 2.7589579
A7: 1ST COMMUNITY BANK | B7: Sherrard | C7: IL | D7: 61281 | E7: 44469 | F7: =YEAR(E7) -> 2021 | G7: 17 | H7: 66909 | I7: 14550 | J7: 66909 | K7: 59859 | L7: 59693 | M7: =IF(H7>1000000,"Large",IF(H7<100000,"Small","Medium")) -> Small | N7: =VLOOKUP(C7,Lookup!$A$2:$D$5,MATCH(M7,Lookup!$A$1:$D$1,0),FALSE) -> 0.09 | O7: =L7*N7 -> 5372.37 | P7: =K7/H7 -> 0.89463301 | Q7: =H7/G7 -> 3935.8235 | R7: =I7/O7 -> 2.7083019
A8: 1ST EQUITY BANK | B8: Skokie | C8: IL | D8: 60076 | E8: 43738 | F8: =YEAR(E8) -> 2019 | G8: 12 | H8: 95211 | I8: 19382 | J8: 95211 | K8: 80418 | L8: 75039 | M8: =IF(H8>1000000,"Large",IF(H8<100000,"Small","Medium")) -> Small | N8: =VLOOKUP(C8,Lookup!$A$2:$D$5,MATCH(M8,Lookup!$A$1:$D$1,0),FALSE) -> 0.09 | O8: =L8*N8 -> 6753.51 | P8: =K8/H8 -> 0.8446293 | Q8: =H8/G8 -> 7934.25 | R8: =I8/O8 -> 2.8699151
A9: 1ST EQUITY BANK | B9: Skokie | C9: IL | D9: 60076 | E9: 44104 | F9: =YEAR(E9) -> 2020 | G9: 10 | H9: 141545 | I9: 28951 | J9: 141545 | K9: 117899 | L9: 101378 | M9: =IF(H9>1000000,"Large",IF(H9<100000,"Small","Medium")) -> Medium | N9: =VLOOKUP(C9,Lookup!$A$2:$D$5,MATCH(M9,Lookup!$A$1:$D$1,0),FALSE) -> 0.08 | O9: =L9*N9 -> 8110.24 | P9: =K9/H9 -> 0.83294359 | Q9: =H9/G9 -> 14154.5 | R9: =I9/O9 -> 3.5696847
A10: 1ST EQUITY BANK | B10: Skokie | C10: IL | D10: 60076 | E10: 44469 | F10: =YEAR(E10) -> 2021 | G10: 10 | H10: 140756 | I10: 32317 | J10: 140756 | K10: 117814 | L10: 104078 | M10: =IF(H10>1000000,"Large",IF(H10<100000,"Small","Medium")) -> Medium | N10: =VLOOKUP(C10,Lookup!$A$2:$D$5,MATCH(M10,Lookup!$A$1:$D$1,0),FALSE) -> 0.08 | O10: =L10*N10 -> 8326.24 | P10: =K10/H10 -> 0.83700872 | Q10: =H10/G10 -> 14075.6 | R10: =I10/O10 -> 3.8813438
A11: 1ST EQUITY BANK NORTHWEST | B11: Buffalo Grove | C11: IL | D11: 60089 | E11: 43738 | F11: =YEAR(E11) -> 2019 | G11: 4 | H11: 40877 | I11: 7973 | J11: 40877 | K11: 32220 | L11: 31131 | M11: =IF(H11>1000000,"Large",IF(H11<100000,"Small","Medium")) -> Small | N11: =VLOOKUP(C11,Lookup!$A$2:$D$5,MATCH(M11,Lookup!$A$1:$D$1,0),FALSE) -> 0.09 | O11: =L11*N11 -> 2801.79 | P11: =K11/H11 -> 0.78821831 | Q11: =H11/G11 -> 10219.25 | R11: =I11/O11 -> 2.8456808
A12: 1ST STATE BANK OF MASON CITY | B12: Mason City | C12: IL | D12: 62664 | E12: 43738 | F12: =YEAR(E12) -> 2019 | G12: 5 | H12: 25319 | I12: 1712 | J12: 25320 | K12: 21384 | L12: 21370 | M12: =IF(H12>1000000,"Large",IF(H12<100000,"Small","Medium")) -> Small | N12: =VLOOKUP(C12,Lookup!$A$2:$D$5,MATCH(M12,Lookup!$A$1:$D$1,0),FALSE) -> 0.09 | O12: =L12*N12 -> 1923.3 | P12: =K12/H12 -> 0.84458312 | Q12: =H12/G12 -> 5063.8 | R12: =I12/O12 -> 0.89013674
A13: 1ST STATE BANK OF MASON CITY | B13: Mason City | C13: IL | D13: 62664 | E13: 44104 | F13: =YEAR(E13) -> 2020 | G13: 7 | H13: 30790 | I13: 1861 | J13: 30790 | K13: 26898 | L13: 22886 | M13: =IF(H13>1000000,"Large",IF(H13<100000,"Small","Medium")) -> Small | N13: =VLOOKUP(C13,Lookup!$A$2:$D$5,MATCH(M13,Lookup!$A$1:$D$1,0),FALSE) -> 0.09 | O13: =L13*N13 -> 2059.74 | P13: =K13/H13 -> 0.87359532 | Q13: =H13/G13 -> 4398.5714 | R13: =I13/O13 -> 0.90351209
... A2413: WSB MUNICIPAL BANK | B2413: Watertown | C2413: NY | D2413: 13601 | E2413: 44469 | F2413: =YEAR(E2413) -> 2021 | G2413: 25 | H2413: 171437 | I2413: 10932 | J2413: 171437 | K2413: 155007 | L2413: 145086 | M2413: =IF(H2413>1000000,"Large",IF(H2413<100000,"Small","Medium")) -> Medium | N2413: =VLOOKUP(C2413,Lookup!$A$2:$D$5,MATCH(M2413,Lookup!$A$1:$D$1,0),FALSE) -> 0.085 | O2413: =L2413*N2413 -> 12332.31 | P2413: =K2413/H2413 -> 0.90416305 | Q2413: =H2413/G2413 -> 6857.48 | R2413: =I2413/O2413 -> 0.88645193

Sheet Lookup
B1: Large | C1: Medium | D1: Small
A2: CA | B2: 0.08 | C2: 0.09 | D2: 0.1
A3: IL | B3: 0.075 | C3: 0.08 | D3: 0.09
A4: MA | B4: 0.08 | C4: 0.085 | D4: 0.095
A5: NY | B5: 0.08 | C5: 0.085 | D5: 0.09

Sheet Question3&4
A3: Row Labels | B3: Average of Cash Requirements
A4: Large | B4: 894969.87 | F4: What was the average cash requirement for Large Banks?
A5: CA | B5: 902145.28 | H5: =B4 -> 894969.87
A6: IL | B6: 577182.99
A7: MA | B7: 589599.09 | F7: What was the average cash requirements for Medium-size banks in California
A8: NY | B8: 1382134.6 | H8: =B10 -> 32913.561
A9: Medium | B9: 26122.116
A10: CA | B10: 32913.561
A11: IL | B11: 20666.909
A12: MA | B12: 34813.125
A13: NY | B13: 30792.806
A14: Small | B14: 4225.1384
A15: CA | B15: 4995.8611
A16: IL | B16: 4255.2447
A17: MA | B17: 4142.4664
A18: NY | B18: 3387.9729
A19: Grand Total | B19: 274958.77

Sheet Question5&6
F2: True/False
A3: Row Labels | B3: Average of Total Asset/Employees
A4: 2019 | B4: 7488.8768 | E4: In 2019, Banks in New York had the highest Average Total Asset/Employee ratio than banks in the other 3 states
A5: CA | B5: 8638.5028 | E5: TRUE
A6: IL | B6: 5767.2853 | E6: in 2020, the Average Asset to Employee ratio for Banks in Illinois was lower than for 2019
A7: MA | B7: 7472.5234 | E7: FALSE
A8: NY | B8: 11345.732
A9: 2020 | B9: 8796.1751
A10: CA | B10: 10441.687
A11: IL | B11: 6783.0189
A12: MA | B12: 8439.5031
A13: NY | B13: 13294.938
A14: 2021 | B14: 9696.227
A15: CA | B15: 12224.993
A16: IL | B16: 7264.3628
A17: MA | B17: 9074.1915
A18: NY | B18: 14681.744
A19: Grand Total | B19: 8633.9223

Sheet Question7
A3: Row Labels | B3: Average of Liabilities /Total Assets
A4: Large | B4: 0.89143185
A5: CA | B5: 0.88169316 | E5: Large Banks in California have higher average Liabilities/Total Asset Ratio than those in Illinois or Massachusetts
A6: IL | B6: 0.89659517 | E6: FALSE
A7: MA | B7: 0.89454904 | E7: Small banks in Massachusetts have lower Average Liabilities/Total Asset Ratio than those in New York and California
A8: NY | B8: 0.89605325 | E8: TRUE
A9: Medium | B9: 0.87751123 | E9: Medium Size Banks in Illinois have higher average Liabilities/Total Assets Ratio than California
A10: CA | B10: 0.86065995 | E10: TRUE
A11: IL | B11: 0.88216865 | E11: Small Banks in Illinois have higher average Liabilities/Total Assets ratios than Medium-size banks in California
A12: MA | B12: 0.87730304 | E12: TRUE
A13: NY | B13: 0.87825413
A14: Small | B14: 0.84223806
A15: CA | B15: 0.74250568
A16: IL | B16: 0.86324802
A17: MA | B17: 0.58003576
A18: NY | B18: 0.74823606
A19: Grand Total | B19: 0.87563425

Sheet Q7A
A3: Row Labels | B3: Average of Total Asset/Employees
A4: Large | B4: 12958.155 | F4: Small banks in California have higher average Total Assets per employee than those in Massechusetts and Illinois
A5: CA | B5: 12544.045 | F5: TRUE
A6: IL | B6: 11171.447
A7: MA | B7: 9693.7735
A8: NY | B8: 17374.791
A9: Medium | B9: 7401.2361
A10: CA | B10: 8509.5261
A11: IL | B11: 6240.73
A12: MA | B12: 7468.9426
A13: NY | B13: 10369.504
A14: Small | B14: 5124.2952
A15: CA | B15: 5943.183
A16: IL | B16: 5221.1433
A17: MA | B17: 4713.2312
... A19: Grand Total | B19: 8633.9223

Sheet Q8
A3: Row Labels | B3: Average of CashBalance/Cash Requirements
A4: 2019 | B4: 3.177512
A5: Large | B5: 5.5977878
A6: Medium | B6: 1.5122993
A7: Small | B7: 4.6732411
A8: 2020 | B8: 5.3732026
A9: Large | B9: 10.192173
A10: Medium | B10: 2.598428
A11: Small | B11: 5.7648842
A12: 2021 | B12: 13.422955
A13: Large | B13: 29.606723
A14: Medium | B14: 4.1750925
A15: Small | B15: 12.047717
A16: Grand Total | B16: 7.2095649

Sheet Q9&10
A3: Average of CashBalance/Cash Requirements | B3: Column Labels
A4: Row Labels | B4: Large | C4: Medium | D4: Small | E4: Grand Total
A5: 2019 | B5: 5.5977878 | C5: 1.5122993 | D5: 4.6732411 | E5: 3.177512
A6: 2020 | B6: 10.192173 | C6: 2.598428 | D6: 5.7648842 | E6: 5.3732026
A7: 2021 | B7: 29.606723 | C7: 4.1750925 | D7: 12.047717 | E7: 13.422955
A8: Grand Total | B8: 15.623843 | C8: 2.718542 | D8: 7.1277545 | E8: 7.2095649
A13: Row Labels | B13: 2019 | C13: 2020 | D13: 2021
A14: Large | B14: 5.5977878 | C14: 10.192173 | D14: 29.606723
A15: Medium | B15: 1.5122993 | C15: 2.598428 | D15: 4.1750925
A16: Small | B16: 4.6732411 | C16: 5.7648842 | D16: 12.047717
A40: Row Labels
A41: Large
A42: Max of CashBalance/Cash Requirements2 | B42: 6753.8051
A43: StdDev of CashBalance/Cash Requirements | B43: 267.54576
A44: Medium
A45: Max of CashBalance/Cash Requirements2 | B45: 854.66667
A46: StdDev of CashBalance/Cash Requirements | B46: 25.520955
A47: Small
A48: Max of CashBalance/Cash Requirements2 | B48: 561.88723
A49: StdDev of CashBalance/Cash Requirements | B49: 37.206222
A50: Total Max of CashBalance/Cash Requirements2 | B50: 6753.8051
A51: Total StdDev of CashBalance/Cash Requirements | B51: 146.28217

Sheet Sheet7
A3: Row Labels | B3: Average of Total Asset/Employees
A4: Large | B4: 12958.155
A5: Medium | B5: 7401.2361
A6: Small | B6: 5124.2952
A7: Grand Total | B7: 8633.9223
